{
  "primary": {
    "50": "#fdf4f8",
    "100": "#fbdde9",
    "200": "#f6b8d3",
    "300": "#f18abc",
    "400": "#ec5da5",
    "500": "#e7338f",
    "600": "#cf1f79",
    "700": "#a51562",
    "800": "#7a0f4a",
    "900": "#4e072f"
  },
  "secondary": {
    "50": "#f2f8ff",
    "100": "#d8ecff",
    "200": "#abd5ff",
    "300": "#7cbcff",
    "400": "#4ea4ff",
    "500": "#1f8cff",
    "600": "#0b6fdb",
    "700": "#0854a7",
    "800": "#053975",
    "900": "#021f44"
  },
  "accent": "#ffe066",
  "neutral": {
    "50": "#f8f9fa",
    "100": "#f1f3f5",
    "200": "#e9ecef",
    "300": "#dee2e6",
    "400": "#ced4da",
    "500": "#adb5bd",
    "600": "#868e96",
    "700": "#495057",
    "800": "#343a40",
    "900": "#212529"
  }
}
